capcha/__init__.py
capcha/abtest/acc.png
capcha/abtest/admin.png
capcha/abtest/hospital_db.db
capcha/abtest/lab.png
capcha/abtest/lab_res.png
capcha/abtest/main.py
capcha/abtest/pac.png
capcha-3.3.dist-info/METADATA
capcha-3.3.dist-info/WHEEL
capcha-3.3.dist-info/top_level.txt
capcha-3.3.dist-info/RECORD
