Metadata-Version: 2.1
Name: capcha
Version: 3.3
Author: BornTheHell
Author-email: 
Classifier: Programming Language :: Python :: 3
Classifier: License :: OSI Approved :: MIT License
Classifier: Operating System :: OS Independent
Requires-Python: >=3.13
